pyxatu/__init__.py
pyxatu/cli.py
pyxatu/client.py
pyxatu/config.json
pyxatu/core.py
pyxatu/docscraper.py
pyxatu/helpers.py
pyxatu/mempoolconnector.py
pyxatu/relayendpoint.py
pyxatu/retriever.py
pyxatu/utils.py
pyxatu/validators.py
pyxatu-1.9.1.dist-info/LICENSE
pyxatu-1.9.1.dist-info/METADATA
pyxatu-1.9.1.dist-info/WHEEL
pyxatu-1.9.1.dist-info/entry_points.txt
pyxatu-1.9.1.dist-info/top_level.txt
pyxatu-1.9.1.dist-info/RECORD
