Metadata-Version: 2.1
Name: pyxatu
Version: 1.9.1
Summary: A Python interface for the Xatu API
Home-page: https://github.com/nerolation/pyxatu
Author: Toni Wahrstätter
Author-email: toni@ethereum.org
Classifier: Programming Language :: Python :: 3
Classifier: Programming Language :: Python :: 3.7
Classifier: License :: OSI Approved :: MIT License
Classifier: Operating System :: OS Independent
Requires-Python: >=3.7
License-File: LICENSE
Requires-Dist: bs4
Requires-Dist: click
Requires-Dist: fastparquet
Requires-Dist: pandas
Requires-Dist: requests
Requires-Dist: tabulate
Requires-Dist: termcolor
Requires-Dist: tqdm
